zoomg.cpython-39-darwin.so
zoomg-2.0.5.dist-info/LICENSE
zoomg-2.0.5.dist-info/METADATA
zoomg-2.0.5.dist-info/WHEEL
zoomg-2.0.5.dist-info/top_level.txt
zoomg-2.0.5.dist-info/RECORD
