Metadata-Version: 2.1
Name: zoomg
Version: 2.0.5
Summary: Restoring room images from virtual background images.
Home-page: https://github.com/Tsuku43/zoomg
Author: Ryusei Ishikawa, Satoki Tsuji
Author-email: UNKNOWN
License: MIT
Keywords: zoom virtual background reconstruction
Platform: UNKNOWN
Requires-Dist: pybind11 (>=2.4)
